package gnu.trove.impl.sync;

import gnu.trove.TCharCollection;
import gnu.trove.function.TCharFunction;
import gnu.trove.iterator.TCharCharIterator;
import gnu.trove.map.TCharCharMap;
import gnu.trove.set.TCharSet;
import java.io.IOException;
import java.io.ObjectOutputStream;
import java.io.Serializable;
import java.util.Map;

public class TSynchronizedCharCharMap
  implements TCharCharMap, Serializable
{
  private static final long serialVersionUID = 1978198479659022715L;
  private final TCharCharMap m;
  final Object mutex;
  
  public TSynchronizedCharCharMap(TCharCharMap m)
  {
    if (m == null) {
      throw new NullPointerException();
    }
    this.m = m;
    this.mutex = this;
  }
  
  public TSynchronizedCharCharMap(TCharCharMap m, Object mutex)
  {
    this.m = m;
    this.mutex = mutex;
  }
  
  /* Error */
  public int size()
  {
    // Byte code:
    //   0: aload_0
    //   1: getfield 37	gnu/trove/impl/sync/TSynchronizedCharCharMap:mutex	Ljava/lang/Object;
    //   4: dup
    //   5: astore_1
    //   6: monitorenter
    //   7: aload_0
    //   8: getfield 35	gnu/trove/impl/sync/TSynchronizedCharCharMap:m	Lgnu/trove/map/TCharCharMap;
    //   11: invokeinterface 44 1 0
    //   16: aload_1
    //   17: monitorexit
    //   18: ireturn
    //   19: astore_2
    //   20: aload_1
    //   21: monitorexit
    //   22: aload_2
    //   23: athrow
    // Line number table:
    //   Java source line #71	-> byte code offset #0
    // Local variable table:
    //   start	length	slot	name	signature
    //   0	24	0	this	TSynchronizedCharCharMap
    //   5	16	1	Ljava/lang/Object;	Object
    //   19	4	2	localObject1	Object
    // Exception table:
    //   from	to	target	type
    //   7	18	19	finally
    //   19	22	19	finally
  }
  
  /* Error */
  public boolean isEmpty()
  {
    // Byte code:
    //   0: aload_0
    //   1: getfield 37	gnu/trove/impl/sync/TSynchronizedCharCharMap:mutex	Ljava/lang/Object;
    //   4: dup
    //   5: astore_1
    //   6: monitorenter
    //   7: aload_0
    //   8: getfield 35	gnu/trove/impl/sync/TSynchronizedCharCharMap:m	Lgnu/trove/map/TCharCharMap;
    //   11: invokeinterface 48 1 0
    //   16: aload_1
    //   17: monitorexit
    //   18: ireturn
    //   19: astore_2
    //   20: aload_1
    //   21: monitorexit
    //   22: aload_2
    //   23: athrow
    // Line number table:
    //   Java source line #74	-> byte code offset #0
    // Local variable table:
    //   start	length	slot	name	signature
    //   0	24	0	this	TSynchronizedCharCharMap
    //   5	16	1	Ljava/lang/Object;	Object
    //   19	4	2	localObject1	Object
    // Exception table:
    //   from	to	target	type
    //   7	18	19	finally
    //   19	22	19	finally
  }
  
  /* Error */
  public boolean containsKey(char key)
  {
    // Byte code:
    //   0: aload_0
    //   1: getfield 37	gnu/trove/impl/sync/TSynchronizedCharCharMap:mutex	Ljava/lang/Object;
    //   4: dup
    //   5: astore_2
    //   6: monitorenter
    //   7: aload_0
    //   8: getfield 35	gnu/trove/impl/sync/TSynchronizedCharCharMap:m	Lgnu/trove/map/TCharCharMap;
    //   11: iload_1
    //   12: invokeinterface 52 2 0
    //   17: aload_2
    //   18: monitorexit
    //   19: ireturn
    //   20: astore_3
    //   21: aload_2
    //   22: monitorexit
    //   23: aload_3
    //   24: athrow
    // Line number table:
    //   Java source line #77	-> byte code offset #0
    // Local variable table:
    //   start	length	slot	name	signature
    //   0	25	0	this	TSynchronizedCharCharMap
    //   0	25	1	key	char
    //   5	17	2	Ljava/lang/Object;	Object
    //   20	4	3	localObject1	Object
    // Exception table:
    //   from	to	target	type
    //   7	19	20	finally
    //   20	23	20	finally
  }
  
  /* Error */
  public boolean containsValue(char value)
  {
    // Byte code:
    //   0: aload_0
    //   1: getfield 37	gnu/trove/impl/sync/TSynchronizedCharCharMap:mutex	Ljava/lang/Object;
    //   4: dup
    //   5: astore_2
    //   6: monitorenter
    //   7: aload_0
    //   8: getfield 35	gnu/trove/impl/sync/TSynchronizedCharCharMap:m	Lgnu/trove/map/TCharCharMap;
    //   11: iload_1
    //   12: invokeinterface 57 2 0
    //   17: aload_2
    //   18: monitorexit
    //   19: ireturn
    //   20: astore_3
    //   21: aload_2
    //   22: monitorexit
    //   23: aload_3
    //   24: athrow
    // Line number table:
    //   Java source line #80	-> byte code offset #0
    // Local variable table:
    //   start	length	slot	name	signature
    //   0	25	0	this	TSynchronizedCharCharMap
    //   0	25	1	value	char
    //   5	17	2	Ljava/lang/Object;	Object
    //   20	4	3	localObject1	Object
    // Exception table:
    //   from	to	target	type
    //   7	19	20	finally
    //   20	23	20	finally
  }
  
  /* Error */
  public char get(char key)
  {
    // Byte code:
    //   0: aload_0
    //   1: getfield 37	gnu/trove/impl/sync/TSynchronizedCharCharMap:mutex	Ljava/lang/Object;
    //   4: dup
    //   5: astore_2
    //   6: monitorenter
    //   7: aload_0
    //   8: getfield 35	gnu/trove/impl/sync/TSynchronizedCharCharMap:m	Lgnu/trove/map/TCharCharMap;
    //   11: iload_1
    //   12: invokeinterface 62 2 0
    //   17: aload_2
    //   18: monitorexit
    //   19: ireturn
    //   20: astore_3
    //   21: aload_2
    //   22: monitorexit
    //   23: aload_3
    //   24: athrow
    // Line number table:
    //   Java source line #83	-> byte code offset #0
    // Local variable table:
    //   start	length	slot	name	signature
    //   0	25	0	this	TSynchronizedCharCharMap
    //   0	25	1	key	char
    //   5	17	2	Ljava/lang/Object;	Object
    //   20	4	3	localObject1	Object
    // Exception table:
    //   from	to	target	type
    //   7	19	20	finally
    //   20	23	20	finally
  }
  
  /* Error */
  public char put(char key, char value)
  {
    // Byte code:
    //   0: aload_0
    //   1: getfield 37	gnu/trove/impl/sync/TSynchronizedCharCharMap:mutex	Ljava/lang/Object;
    //   4: dup
    //   5: astore_3
    //   6: monitorenter
    //   7: aload_0
    //   8: getfield 35	gnu/trove/impl/sync/TSynchronizedCharCharMap:m	Lgnu/trove/map/TCharCharMap;
    //   11: iload_1
    //   12: iload_2
    //   13: invokeinterface 66 3 0
    //   18: aload_3
    //   19: monitorexit
    //   20: ireturn
    //   21: astore 4
    //   23: aload_3
    //   24: monitorexit
    //   25: aload 4
    //   27: athrow
    // Line number table:
    //   Java source line #87	-> byte code offset #0
    // Local variable table:
    //   start	length	slot	name	signature
    //   0	28	0	this	TSynchronizedCharCharMap
    //   0	28	1	key	char
    //   0	28	2	value	char
    //   5	19	3	Ljava/lang/Object;	Object
    //   21	5	4	localObject1	Object
    // Exception table:
    //   from	to	target	type
    //   7	20	21	finally
    //   21	25	21	finally
  }
  
  /* Error */
  public char remove(char key)
  {
    // Byte code:
    //   0: aload_0
    //   1: getfield 37	gnu/trove/impl/sync/TSynchronizedCharCharMap:mutex	Ljava/lang/Object;
    //   4: dup
    //   5: astore_2
    //   6: monitorenter
    //   7: aload_0
    //   8: getfield 35	gnu/trove/impl/sync/TSynchronizedCharCharMap:m	Lgnu/trove/map/TCharCharMap;
    //   11: iload_1
    //   12: invokeinterface 69 2 0
    //   17: aload_2
    //   18: monitorexit
    //   19: ireturn
    //   20: astore_3
    //   21: aload_2
    //   22: monitorexit
    //   23: aload_3
    //   24: athrow
    // Line number table:
    //   Java source line #90	-> byte code offset #0
    // Local variable table:
    //   start	length	slot	name	signature
    //   0	25	0	this	TSynchronizedCharCharMap
    //   0	25	1	key	char
    //   5	17	2	Ljava/lang/Object;	Object
    //   20	4	3	localObject1	Object
    // Exception table:
    //   from	to	target	type
    //   7	19	20	finally
    //   20	23	20	finally
  }
  
  public void putAll(Map<? extends Character, ? extends Character> map)
  {
    synchronized (this.mutex)
    {
      this.m.putAll(map);
    }
  }
  
  public void putAll(TCharCharMap map)
  {
    synchronized (this.mutex)
    {
      this.m.putAll(map);
    }
  }
  
  public void clear()
  {
    synchronized (this.mutex)
    {
      this.m.clear();
    }
  }
  
  private transient TCharSet keySet = null;
  private transient TCharCollection values = null;
  
  public TCharSet keySet()
  {
    synchronized (this.mutex)
    {
      if (this.keySet == null) {
        this.keySet = new TSynchronizedCharSet(this.m.keySet(), this.mutex);
      }
      return this.keySet;
    }
  }
  
  /* Error */
  public char[] keys()
  {
    // Byte code:
    //   0: aload_0
    //   1: getfield 37	gnu/trove/impl/sync/TSynchronizedCharCharMap:mutex	Ljava/lang/Object;
    //   4: dup
    //   5: astore_1
    //   6: monitorenter
    //   7: aload_0
    //   8: getfield 35	gnu/trove/impl/sync/TSynchronizedCharCharMap:m	Lgnu/trove/map/TCharCharMap;
    //   11: invokeinterface 93 1 0
    //   16: aload_1
    //   17: monitorexit
    //   18: areturn
    //   19: astore_2
    //   20: aload_1
    //   21: monitorexit
    //   22: aload_2
    //   23: athrow
    // Line number table:
    //   Java source line #113	-> byte code offset #0
    // Local variable table:
    //   start	length	slot	name	signature
    //   0	24	0	this	TSynchronizedCharCharMap
    //   5	16	1	Ljava/lang/Object;	Object
    //   19	4	2	localObject1	Object
    // Exception table:
    //   from	to	target	type
    //   7	18	19	finally
    //   19	22	19	finally
  }
  
  /* Error */
  public char[] keys(char[] array)
  {
    // Byte code:
    //   0: aload_0
    //   1: getfield 37	gnu/trove/impl/sync/TSynchronizedCharCharMap:mutex	Ljava/lang/Object;
    //   4: dup
    //   5: astore_2
    //   6: monitorenter
    //   7: aload_0
    //   8: getfield 35	gnu/trove/impl/sync/TSynchronizedCharCharMap:m	Lgnu/trove/map/TCharCharMap;
    //   11: aload_1
    //   12: invokeinterface 96 2 0
    //   17: aload_2
    //   18: monitorexit
    //   19: areturn
    //   20: astore_3
    //   21: aload_2
    //   22: monitorexit
    //   23: aload_3
    //   24: athrow
    // Line number table:
    //   Java source line #116	-> byte code offset #0
    // Local variable table:
    //   start	length	slot	name	signature
    //   0	25	0	this	TSynchronizedCharCharMap
    //   0	25	1	array	char[]
    //   5	17	2	Ljava/lang/Object;	Object
    //   20	4	3	localObject1	Object
    // Exception table:
    //   from	to	target	type
    //   7	19	20	finally
    //   20	23	20	finally
  }
  
  public TCharCollection valueCollection()
  {
    synchronized (this.mutex)
    {
      if (this.values == null) {
        this.values = new TSynchronizedCharCollection(this.m.valueCollection(), this.mutex);
      }
      return this.values;
    }
  }
  
  /* Error */
  public char[] values()
  {
    // Byte code:
    //   0: aload_0
    //   1: getfield 37	gnu/trove/impl/sync/TSynchronizedCharCharMap:mutex	Ljava/lang/Object;
    //   4: dup
    //   5: astore_1
    //   6: monitorenter
    //   7: aload_0
    //   8: getfield 35	gnu/trove/impl/sync/TSynchronizedCharCharMap:m	Lgnu/trove/map/TCharCharMap;
    //   11: invokeinterface 109 1 0
    //   16: aload_1
    //   17: monitorexit
    //   18: areturn
    //   19: astore_2
    //   20: aload_1
    //   21: monitorexit
    //   22: aload_2
    //   23: athrow
    // Line number table:
    //   Java source line #127	-> byte code offset #0
    // Local variable table:
    //   start	length	slot	name	signature
    //   0	24	0	this	TSynchronizedCharCharMap
    //   5	16	1	Ljava/lang/Object;	Object
    //   19	4	2	localObject1	Object
    // Exception table:
    //   from	to	target	type
    //   7	18	19	finally
    //   19	22	19	finally
  }
  
  /* Error */
  public char[] values(char[] array)
  {
    // Byte code:
    //   0: aload_0
    //   1: getfield 37	gnu/trove/impl/sync/TSynchronizedCharCharMap:mutex	Ljava/lang/Object;
    //   4: dup
    //   5: astore_2
    //   6: monitorenter
    //   7: aload_0
    //   8: getfield 35	gnu/trove/impl/sync/TSynchronizedCharCharMap:m	Lgnu/trove/map/TCharCharMap;
    //   11: aload_1
    //   12: invokeinterface 111 2 0
    //   17: aload_2
    //   18: monitorexit
    //   19: areturn
    //   20: astore_3
    //   21: aload_2
    //   22: monitorexit
    //   23: aload_3
    //   24: athrow
    // Line number table:
    //   Java source line #130	-> byte code offset #0
    // Local variable table:
    //   start	length	slot	name	signature
    //   0	25	0	this	TSynchronizedCharCharMap
    //   0	25	1	array	char[]
    //   5	17	2	Ljava/lang/Object;	Object
    //   20	4	3	localObject1	Object
    // Exception table:
    //   from	to	target	type
    //   7	19	20	finally
    //   20	23	20	finally
  }
  
  public TCharCharIterator iterator()
  {
    return this.m.iterator();
  }
  
  public char getNoEntryKey()
  {
    return this.m.getNoEntryKey();
  }
  
  public char getNoEntryValue()
  {
    return this.m.getNoEntryValue();
  }
  
  /* Error */
  public char putIfAbsent(char key, char value)
  {
    // Byte code:
    //   0: aload_0
    //   1: getfield 37	gnu/trove/impl/sync/TSynchronizedCharCharMap:mutex	Ljava/lang/Object;
    //   4: dup
    //   5: astore_3
    //   6: monitorenter
    //   7: aload_0
    //   8: getfield 35	gnu/trove/impl/sync/TSynchronizedCharCharMap:m	Lgnu/trove/map/TCharCharMap;
    //   11: iload_1
    //   12: iload_2
    //   13: invokeinterface 125 3 0
    //   18: aload_3
    //   19: monitorexit
    //   20: ireturn
    //   21: astore 4
    //   23: aload_3
    //   24: monitorexit
    //   25: aload 4
    //   27: athrow
    // Line number table:
    //   Java source line #142	-> byte code offset #0
    // Local variable table:
    //   start	length	slot	name	signature
    //   0	28	0	this	TSynchronizedCharCharMap
    //   0	28	1	key	char
    //   0	28	2	value	char
    //   5	19	3	Ljava/lang/Object;	Object
    //   21	5	4	localObject1	Object
    // Exception table:
    //   from	to	target	type
    //   7	20	21	finally
    //   21	25	21	finally
  }
  
  /* Error */
  public boolean forEachKey(gnu.trove.procedure.TCharProcedure procedure)
  {
    // Byte code:
    //   0: aload_0
    //   1: getfield 37	gnu/trove/impl/sync/TSynchronizedCharCharMap:mutex	Ljava/lang/Object;
    //   4: dup
    //   5: astore_2
    //   6: monitorenter
    //   7: aload_0
    //   8: getfield 35	gnu/trove/impl/sync/TSynchronizedCharCharMap:m	Lgnu/trove/map/TCharCharMap;
    //   11: aload_1
    //   12: invokeinterface 129 2 0
    //   17: aload_2
    //   18: monitorexit
    //   19: ireturn
    //   20: astore_3
    //   21: aload_2
    //   22: monitorexit
    //   23: aload_3
    //   24: athrow
    // Line number table:
    //   Java source line #145	-> byte code offset #0
    // Local variable table:
    //   start	length	slot	name	signature
    //   0	25	0	this	TSynchronizedCharCharMap
    //   0	25	1	procedure	gnu.trove.procedure.TCharProcedure
    //   5	17	2	Ljava/lang/Object;	Object
    //   20	4	3	localObject1	Object
    // Exception table:
    //   from	to	target	type
    //   7	19	20	finally
    //   20	23	20	finally
  }
  
  /* Error */
  public boolean forEachValue(gnu.trove.procedure.TCharProcedure procedure)
  {
    // Byte code:
    //   0: aload_0
    //   1: getfield 37	gnu/trove/impl/sync/TSynchronizedCharCharMap:mutex	Ljava/lang/Object;
    //   4: dup
    //   5: astore_2
    //   6: monitorenter
    //   7: aload_0
    //   8: getfield 35	gnu/trove/impl/sync/TSynchronizedCharCharMap:m	Lgnu/trove/map/TCharCharMap;
    //   11: aload_1
    //   12: invokeinterface 134 2 0
    //   17: aload_2
    //   18: monitorexit
    //   19: ireturn
    //   20: astore_3
    //   21: aload_2
    //   22: monitorexit
    //   23: aload_3
    //   24: athrow
    // Line number table:
    //   Java source line #148	-> byte code offset #0
    // Local variable table:
    //   start	length	slot	name	signature
    //   0	25	0	this	TSynchronizedCharCharMap
    //   0	25	1	procedure	gnu.trove.procedure.TCharProcedure
    //   5	17	2	Ljava/lang/Object;	Object
    //   20	4	3	localObject1	Object
    // Exception table:
    //   from	to	target	type
    //   7	19	20	finally
    //   20	23	20	finally
  }
  
  /* Error */
  public boolean forEachEntry(gnu.trove.procedure.TCharCharProcedure procedure)
  {
    // Byte code:
    //   0: aload_0
    //   1: getfield 37	gnu/trove/impl/sync/TSynchronizedCharCharMap:mutex	Ljava/lang/Object;
    //   4: dup
    //   5: astore_2
    //   6: monitorenter
    //   7: aload_0
    //   8: getfield 35	gnu/trove/impl/sync/TSynchronizedCharCharMap:m	Lgnu/trove/map/TCharCharMap;
    //   11: aload_1
    //   12: invokeinterface 138 2 0
    //   17: aload_2
    //   18: monitorexit
    //   19: ireturn
    //   20: astore_3
    //   21: aload_2
    //   22: monitorexit
    //   23: aload_3
    //   24: athrow
    // Line number table:
    //   Java source line #151	-> byte code offset #0
    // Local variable table:
    //   start	length	slot	name	signature
    //   0	25	0	this	TSynchronizedCharCharMap
    //   0	25	1	procedure	gnu.trove.procedure.TCharCharProcedure
    //   5	17	2	Ljava/lang/Object;	Object
    //   20	4	3	localObject1	Object
    // Exception table:
    //   from	to	target	type
    //   7	19	20	finally
    //   20	23	20	finally
  }
  
  public void transformValues(TCharFunction function)
  {
    synchronized (this.mutex)
    {
      this.m.transformValues(function);
    }
  }
  
  /* Error */
  public boolean retainEntries(gnu.trove.procedure.TCharCharProcedure procedure)
  {
    // Byte code:
    //   0: aload_0
    //   1: getfield 37	gnu/trove/impl/sync/TSynchronizedCharCharMap:mutex	Ljava/lang/Object;
    //   4: dup
    //   5: astore_2
    //   6: monitorenter
    //   7: aload_0
    //   8: getfield 35	gnu/trove/impl/sync/TSynchronizedCharCharMap:m	Lgnu/trove/map/TCharCharMap;
    //   11: aload_1
    //   12: invokeinterface 148 2 0
    //   17: aload_2
    //   18: monitorexit
    //   19: ireturn
    //   20: astore_3
    //   21: aload_2
    //   22: monitorexit
    //   23: aload_3
    //   24: athrow
    // Line number table:
    //   Java source line #157	-> byte code offset #0
    // Local variable table:
    //   start	length	slot	name	signature
    //   0	25	0	this	TSynchronizedCharCharMap
    //   0	25	1	procedure	gnu.trove.procedure.TCharCharProcedure
    //   5	17	2	Ljava/lang/Object;	Object
    //   20	4	3	localObject1	Object
    // Exception table:
    //   from	to	target	type
    //   7	19	20	finally
    //   20	23	20	finally
  }
  
  /* Error */
  public boolean increment(char key)
  {
    // Byte code:
    //   0: aload_0
    //   1: getfield 37	gnu/trove/impl/sync/TSynchronizedCharCharMap:mutex	Ljava/lang/Object;
    //   4: dup
    //   5: astore_2
    //   6: monitorenter
    //   7: aload_0
    //   8: getfield 35	gnu/trove/impl/sync/TSynchronizedCharCharMap:m	Lgnu/trove/map/TCharCharMap;
    //   11: iload_1
    //   12: invokeinterface 151 2 0
    //   17: aload_2
    //   18: monitorexit
    //   19: ireturn
    //   20: astore_3
    //   21: aload_2
    //   22: monitorexit
    //   23: aload_3
    //   24: athrow
    // Line number table:
    //   Java source line #160	-> byte code offset #0
    // Local variable table:
    //   start	length	slot	name	signature
    //   0	25	0	this	TSynchronizedCharCharMap
    //   0	25	1	key	char
    //   5	17	2	Ljava/lang/Object;	Object
    //   20	4	3	localObject1	Object
    // Exception table:
    //   from	to	target	type
    //   7	19	20	finally
    //   20	23	20	finally
  }
  
  /* Error */
  public boolean adjustValue(char key, char amount)
  {
    // Byte code:
    //   0: aload_0
    //   1: getfield 37	gnu/trove/impl/sync/TSynchronizedCharCharMap:mutex	Ljava/lang/Object;
    //   4: dup
    //   5: astore_3
    //   6: monitorenter
    //   7: aload_0
    //   8: getfield 35	gnu/trove/impl/sync/TSynchronizedCharCharMap:m	Lgnu/trove/map/TCharCharMap;
    //   11: iload_1
    //   12: iload_2
    //   13: invokeinterface 155 3 0
    //   18: aload_3
    //   19: monitorexit
    //   20: ireturn
    //   21: astore 4
    //   23: aload_3
    //   24: monitorexit
    //   25: aload 4
    //   27: athrow
    // Line number table:
    //   Java source line #163	-> byte code offset #0
    // Local variable table:
    //   start	length	slot	name	signature
    //   0	28	0	this	TSynchronizedCharCharMap
    //   0	28	1	key	char
    //   0	28	2	amount	char
    //   5	19	3	Ljava/lang/Object;	Object
    //   21	5	4	localObject1	Object
    // Exception table:
    //   from	to	target	type
    //   7	20	21	finally
    //   21	25	21	finally
  }
  
  /* Error */
  public char adjustOrPutValue(char key, char adjust_amount, char put_amount)
  {
    // Byte code:
    //   0: aload_0
    //   1: getfield 37	gnu/trove/impl/sync/TSynchronizedCharCharMap:mutex	Ljava/lang/Object;
    //   4: dup
    //   5: astore 4
    //   7: monitorenter
    //   8: aload_0
    //   9: getfield 35	gnu/trove/impl/sync/TSynchronizedCharCharMap:m	Lgnu/trove/map/TCharCharMap;
    //   12: iload_1
    //   13: iload_2
    //   14: iload_3
    //   15: invokeinterface 160 4 0
    //   20: aload 4
    //   22: monitorexit
    //   23: ireturn
    //   24: astore 5
    //   26: aload 4
    //   28: monitorexit
    //   29: aload 5
    //   31: athrow
    // Line number table:
    //   Java source line #166	-> byte code offset #0
    // Local variable table:
    //   start	length	slot	name	signature
    //   0	32	0	this	TSynchronizedCharCharMap
    //   0	32	1	key	char
    //   0	32	2	adjust_amount	char
    //   0	32	3	put_amount	char
    //   5	22	4	Ljava/lang/Object;	Object
    //   24	6	5	localObject1	Object
    // Exception table:
    //   from	to	target	type
    //   8	23	24	finally
    //   24	29	24	finally
  }
  
  /* Error */
  public boolean equals(Object o)
  {
    // Byte code:
    //   0: aload_0
    //   1: getfield 37	gnu/trove/impl/sync/TSynchronizedCharCharMap:mutex	Ljava/lang/Object;
    //   4: dup
    //   5: astore_2
    //   6: monitorenter
    //   7: aload_0
    //   8: getfield 35	gnu/trove/impl/sync/TSynchronizedCharCharMap:m	Lgnu/trove/map/TCharCharMap;
    //   11: aload_1
    //   12: invokevirtual 166	java/lang/Object:equals	(Ljava/lang/Object;)Z
    //   15: aload_2
    //   16: monitorexit
    //   17: ireturn
    //   18: astore_3
    //   19: aload_2
    //   20: monitorexit
    //   21: aload_3
    //   22: athrow
    // Line number table:
    //   Java source line #170	-> byte code offset #0
    // Local variable table:
    //   start	length	slot	name	signature
    //   0	23	0	this	TSynchronizedCharCharMap
    //   0	23	1	o	Object
    //   5	15	2	Ljava/lang/Object;	Object
    //   18	4	3	localObject1	Object
    // Exception table:
    //   from	to	target	type
    //   7	17	18	finally
    //   18	21	18	finally
  }
  
  /* Error */
  public int hashCode()
  {
    // Byte code:
    //   0: aload_0
    //   1: getfield 37	gnu/trove/impl/sync/TSynchronizedCharCharMap:mutex	Ljava/lang/Object;
    //   4: dup
    //   5: astore_1
    //   6: monitorenter
    //   7: aload_0
    //   8: getfield 35	gnu/trove/impl/sync/TSynchronizedCharCharMap:m	Lgnu/trove/map/TCharCharMap;
    //   11: invokevirtual 170	java/lang/Object:hashCode	()I
    //   14: aload_1
    //   15: monitorexit
    //   16: ireturn
    //   17: astore_2
    //   18: aload_1
    //   19: monitorexit
    //   20: aload_2
    //   21: athrow
    // Line number table:
    //   Java source line #173	-> byte code offset #0
    // Local variable table:
    //   start	length	slot	name	signature
    //   0	22	0	this	TSynchronizedCharCharMap
    //   5	14	1	Ljava/lang/Object;	Object
    //   17	4	2	localObject1	Object
    // Exception table:
    //   from	to	target	type
    //   7	16	17	finally
    //   17	20	17	finally
  }
  
  /* Error */
  public String toString()
  {
    // Byte code:
    //   0: aload_0
    //   1: getfield 37	gnu/trove/impl/sync/TSynchronizedCharCharMap:mutex	Ljava/lang/Object;
    //   4: dup
    //   5: astore_1
    //   6: monitorenter
    //   7: aload_0
    //   8: getfield 35	gnu/trove/impl/sync/TSynchronizedCharCharMap:m	Lgnu/trove/map/TCharCharMap;
    //   11: invokevirtual 174	java/lang/Object:toString	()Ljava/lang/String;
    //   14: aload_1
    //   15: monitorexit
    //   16: areturn
    //   17: astore_2
    //   18: aload_1
    //   19: monitorexit
    //   20: aload_2
    //   21: athrow
    // Line number table:
    //   Java source line #176	-> byte code offset #0
    // Local variable table:
    //   start	length	slot	name	signature
    //   0	22	0	this	TSynchronizedCharCharMap
    //   5	14	1	Ljava/lang/Object;	Object
    //   17	4	2	localObject1	Object
    // Exception table:
    //   from	to	target	type
    //   7	16	17	finally
    //   17	20	17	finally
  }
  
  private void writeObject(ObjectOutputStream s)
    throws IOException
  {
    synchronized (this.mutex)
    {
      s.defaultWriteObject();
    }
  }
}
