package gnu.trove.impl.sync;

import gnu.trove.TShortCollection;
import gnu.trove.function.TShortFunction;
import gnu.trove.iterator.TDoubleShortIterator;
import gnu.trove.map.TDoubleShortMap;
import gnu.trove.set.TDoubleSet;
import java.io.IOException;
import java.io.ObjectOutputStream;
import java.io.Serializable;
import java.util.Map;

public class TSynchronizedDoubleShortMap
  implements TDoubleShortMap, Serializable
{
  private static final long serialVersionUID = 1978198479659022715L;
  private final TDoubleShortMap m;
  final Object mutex;
  
  public TSynchronizedDoubleShortMap(TDoubleShortMap m)
  {
    if (m == null) {
      throw new NullPointerException();
    }
    this.m = m;
    this.mutex = this;
  }
  
  public TSynchronizedDoubleShortMap(TDoubleShortMap m, Object mutex)
  {
    this.m = m;
    this.mutex = mutex;
  }
  
  /* Error */
  public int size()
  {
    // Byte code:
    //   0: aload_0
    //   1: getfield 37	gnu/trove/impl/sync/TSynchronizedDoubleShortMap:mutex	Ljava/lang/Object;
    //   4: dup
    //   5: astore_1
    //   6: monitorenter
    //   7: aload_0
    //   8: getfield 35	gnu/trove/impl/sync/TSynchronizedDoubleShortMap:m	Lgnu/trove/map/TDoubleShortMap;
    //   11: invokeinterface 44 1 0
    //   16: aload_1
    //   17: monitorexit
    //   18: ireturn
    //   19: astore_2
    //   20: aload_1
    //   21: monitorexit
    //   22: aload_2
    //   23: athrow
    // Line number table:
    //   Java source line #71	-> byte code offset #0
    // Local variable table:
    //   start	length	slot	name	signature
    //   0	24	0	this	TSynchronizedDoubleShortMap
    //   5	16	1	Ljava/lang/Object;	Object
    //   19	4	2	localObject1	Object
    // Exception table:
    //   from	to	target	type
    //   7	18	19	finally
    //   19	22	19	finally
  }
  
  /* Error */
  public boolean isEmpty()
  {
    // Byte code:
    //   0: aload_0
    //   1: getfield 37	gnu/trove/impl/sync/TSynchronizedDoubleShortMap:mutex	Ljava/lang/Object;
    //   4: dup
    //   5: astore_1
    //   6: monitorenter
    //   7: aload_0
    //   8: getfield 35	gnu/trove/impl/sync/TSynchronizedDoubleShortMap:m	Lgnu/trove/map/TDoubleShortMap;
    //   11: invokeinterface 48 1 0
    //   16: aload_1
    //   17: monitorexit
    //   18: ireturn
    //   19: astore_2
    //   20: aload_1
    //   21: monitorexit
    //   22: aload_2
    //   23: athrow
    // Line number table:
    //   Java source line #74	-> byte code offset #0
    // Local variable table:
    //   start	length	slot	name	signature
    //   0	24	0	this	TSynchronizedDoubleShortMap
    //   5	16	1	Ljava/lang/Object;	Object
    //   19	4	2	localObject1	Object
    // Exception table:
    //   from	to	target	type
    //   7	18	19	finally
    //   19	22	19	finally
  }
  
  /* Error */
  public boolean containsKey(double key)
  {
    // Byte code:
    //   0: aload_0
    //   1: getfield 37	gnu/trove/impl/sync/TSynchronizedDoubleShortMap:mutex	Ljava/lang/Object;
    //   4: dup
    //   5: astore_3
    //   6: monitorenter
    //   7: aload_0
    //   8: getfield 35	gnu/trove/impl/sync/TSynchronizedDoubleShortMap:m	Lgnu/trove/map/TDoubleShortMap;
    //   11: dload_1
    //   12: invokeinterface 52 3 0
    //   17: aload_3
    //   18: monitorexit
    //   19: ireturn
    //   20: astore 4
    //   22: aload_3
    //   23: monitorexit
    //   24: aload 4
    //   26: athrow
    // Line number table:
    //   Java source line #77	-> byte code offset #0
    // Local variable table:
    //   start	length	slot	name	signature
    //   0	27	0	this	TSynchronizedDoubleShortMap
    //   0	27	1	key	double
    //   5	18	3	Ljava/lang/Object;	Object
    //   20	5	4	localObject1	Object
    // Exception table:
    //   from	to	target	type
    //   7	19	20	finally
    //   20	24	20	finally
  }
  
  /* Error */
  public boolean containsValue(short value)
  {
    // Byte code:
    //   0: aload_0
    //   1: getfield 37	gnu/trove/impl/sync/TSynchronizedDoubleShortMap:mutex	Ljava/lang/Object;
    //   4: dup
    //   5: astore_2
    //   6: monitorenter
    //   7: aload_0
    //   8: getfield 35	gnu/trove/impl/sync/TSynchronizedDoubleShortMap:m	Lgnu/trove/map/TDoubleShortMap;
    //   11: iload_1
    //   12: invokeinterface 58 2 0
    //   17: aload_2
    //   18: monitorexit
    //   19: ireturn
    //   20: astore_3
    //   21: aload_2
    //   22: monitorexit
    //   23: aload_3
    //   24: athrow
    // Line number table:
    //   Java source line #80	-> byte code offset #0
    // Local variable table:
    //   start	length	slot	name	signature
    //   0	25	0	this	TSynchronizedDoubleShortMap
    //   0	25	1	value	short
    //   5	17	2	Ljava/lang/Object;	Object
    //   20	4	3	localObject1	Object
    // Exception table:
    //   from	to	target	type
    //   7	19	20	finally
    //   20	23	20	finally
  }
  
  /* Error */
  public short get(double key)
  {
    // Byte code:
    //   0: aload_0
    //   1: getfield 37	gnu/trove/impl/sync/TSynchronizedDoubleShortMap:mutex	Ljava/lang/Object;
    //   4: dup
    //   5: astore_3
    //   6: monitorenter
    //   7: aload_0
    //   8: getfield 35	gnu/trove/impl/sync/TSynchronizedDoubleShortMap:m	Lgnu/trove/map/TDoubleShortMap;
    //   11: dload_1
    //   12: invokeinterface 64 3 0
    //   17: aload_3
    //   18: monitorexit
    //   19: ireturn
    //   20: astore 4
    //   22: aload_3
    //   23: monitorexit
    //   24: aload 4
    //   26: athrow
    // Line number table:
    //   Java source line #83	-> byte code offset #0
    // Local variable table:
    //   start	length	slot	name	signature
    //   0	27	0	this	TSynchronizedDoubleShortMap
    //   0	27	1	key	double
    //   5	18	3	Ljava/lang/Object;	Object
    //   20	5	4	localObject1	Object
    // Exception table:
    //   from	to	target	type
    //   7	19	20	finally
    //   20	24	20	finally
  }
  
  /* Error */
  public short put(double key, short value)
  {
    // Byte code:
    //   0: aload_0
    //   1: getfield 37	gnu/trove/impl/sync/TSynchronizedDoubleShortMap:mutex	Ljava/lang/Object;
    //   4: dup
    //   5: astore 4
    //   7: monitorenter
    //   8: aload_0
    //   9: getfield 35	gnu/trove/impl/sync/TSynchronizedDoubleShortMap:m	Lgnu/trove/map/TDoubleShortMap;
    //   12: dload_1
    //   13: iload_3
    //   14: invokeinterface 68 4 0
    //   19: aload 4
    //   21: monitorexit
    //   22: ireturn
    //   23: astore 5
    //   25: aload 4
    //   27: monitorexit
    //   28: aload 5
    //   30: athrow
    // Line number table:
    //   Java source line #87	-> byte code offset #0
    // Local variable table:
    //   start	length	slot	name	signature
    //   0	31	0	this	TSynchronizedDoubleShortMap
    //   0	31	1	key	double
    //   0	31	3	value	short
    //   5	21	4	Ljava/lang/Object;	Object
    //   23	6	5	localObject1	Object
    // Exception table:
    //   from	to	target	type
    //   8	22	23	finally
    //   23	28	23	finally
  }
  
  /* Error */
  public short remove(double key)
  {
    // Byte code:
    //   0: aload_0
    //   1: getfield 37	gnu/trove/impl/sync/TSynchronizedDoubleShortMap:mutex	Ljava/lang/Object;
    //   4: dup
    //   5: astore_3
    //   6: monitorenter
    //   7: aload_0
    //   8: getfield 35	gnu/trove/impl/sync/TSynchronizedDoubleShortMap:m	Lgnu/trove/map/TDoubleShortMap;
    //   11: dload_1
    //   12: invokeinterface 71 3 0
    //   17: aload_3
    //   18: monitorexit
    //   19: ireturn
    //   20: astore 4
    //   22: aload_3
    //   23: monitorexit
    //   24: aload 4
    //   26: athrow
    // Line number table:
    //   Java source line #90	-> byte code offset #0
    // Local variable table:
    //   start	length	slot	name	signature
    //   0	27	0	this	TSynchronizedDoubleShortMap
    //   0	27	1	key	double
    //   5	18	3	Ljava/lang/Object;	Object
    //   20	5	4	localObject1	Object
    // Exception table:
    //   from	to	target	type
    //   7	19	20	finally
    //   20	24	20	finally
  }
  
  public void putAll(Map<? extends Double, ? extends Short> map)
  {
    synchronized (this.mutex)
    {
      this.m.putAll(map);
    }
  }
  
  public void putAll(TDoubleShortMap map)
  {
    synchronized (this.mutex)
    {
      this.m.putAll(map);
    }
  }
  
  public void clear()
  {
    synchronized (this.mutex)
    {
      this.m.clear();
    }
  }
  
  private transient TDoubleSet keySet = null;
  private transient TShortCollection values = null;
  
  public TDoubleSet keySet()
  {
    synchronized (this.mutex)
    {
      if (this.keySet == null) {
        this.keySet = new TSynchronizedDoubleSet(this.m.keySet(), this.mutex);
      }
      return this.keySet;
    }
  }
  
  /* Error */
  public double[] keys()
  {
    // Byte code:
    //   0: aload_0
    //   1: getfield 37	gnu/trove/impl/sync/TSynchronizedDoubleShortMap:mutex	Ljava/lang/Object;
    //   4: dup
    //   5: astore_1
    //   6: monitorenter
    //   7: aload_0
    //   8: getfield 35	gnu/trove/impl/sync/TSynchronizedDoubleShortMap:m	Lgnu/trove/map/TDoubleShortMap;
    //   11: invokeinterface 95 1 0
    //   16: aload_1
    //   17: monitorexit
    //   18: areturn
    //   19: astore_2
    //   20: aload_1
    //   21: monitorexit
    //   22: aload_2
    //   23: athrow
    // Line number table:
    //   Java source line #113	-> byte code offset #0
    // Local variable table:
    //   start	length	slot	name	signature
    //   0	24	0	this	TSynchronizedDoubleShortMap
    //   5	16	1	Ljava/lang/Object;	Object
    //   19	4	2	localObject1	Object
    // Exception table:
    //   from	to	target	type
    //   7	18	19	finally
    //   19	22	19	finally
  }
  
  /* Error */
  public double[] keys(double[] array)
  {
    // Byte code:
    //   0: aload_0
    //   1: getfield 37	gnu/trove/impl/sync/TSynchronizedDoubleShortMap:mutex	Ljava/lang/Object;
    //   4: dup
    //   5: astore_2
    //   6: monitorenter
    //   7: aload_0
    //   8: getfield 35	gnu/trove/impl/sync/TSynchronizedDoubleShortMap:m	Lgnu/trove/map/TDoubleShortMap;
    //   11: aload_1
    //   12: invokeinterface 98 2 0
    //   17: aload_2
    //   18: monitorexit
    //   19: areturn
    //   20: astore_3
    //   21: aload_2
    //   22: monitorexit
    //   23: aload_3
    //   24: athrow
    // Line number table:
    //   Java source line #116	-> byte code offset #0
    // Local variable table:
    //   start	length	slot	name	signature
    //   0	25	0	this	TSynchronizedDoubleShortMap
    //   0	25	1	array	double[]
    //   5	17	2	Ljava/lang/Object;	Object
    //   20	4	3	localObject1	Object
    // Exception table:
    //   from	to	target	type
    //   7	19	20	finally
    //   20	23	20	finally
  }
  
  public TShortCollection valueCollection()
  {
    synchronized (this.mutex)
    {
      if (this.values == null) {
        this.values = new TSynchronizedShortCollection(this.m.valueCollection(), this.mutex);
      }
      return this.values;
    }
  }
  
  /* Error */
  public short[] values()
  {
    // Byte code:
    //   0: aload_0
    //   1: getfield 37	gnu/trove/impl/sync/TSynchronizedDoubleShortMap:mutex	Ljava/lang/Object;
    //   4: dup
    //   5: astore_1
    //   6: monitorenter
    //   7: aload_0
    //   8: getfield 35	gnu/trove/impl/sync/TSynchronizedDoubleShortMap:m	Lgnu/trove/map/TDoubleShortMap;
    //   11: invokeinterface 112 1 0
    //   16: aload_1
    //   17: monitorexit
    //   18: areturn
    //   19: astore_2
    //   20: aload_1
    //   21: monitorexit
    //   22: aload_2
    //   23: athrow
    // Line number table:
    //   Java source line #127	-> byte code offset #0
    // Local variable table:
    //   start	length	slot	name	signature
    //   0	24	0	this	TSynchronizedDoubleShortMap
    //   5	16	1	Ljava/lang/Object;	Object
    //   19	4	2	localObject1	Object
    // Exception table:
    //   from	to	target	type
    //   7	18	19	finally
    //   19	22	19	finally
  }
  
  /* Error */
  public short[] values(short[] array)
  {
    // Byte code:
    //   0: aload_0
    //   1: getfield 37	gnu/trove/impl/sync/TSynchronizedDoubleShortMap:mutex	Ljava/lang/Object;
    //   4: dup
    //   5: astore_2
    //   6: monitorenter
    //   7: aload_0
    //   8: getfield 35	gnu/trove/impl/sync/TSynchronizedDoubleShortMap:m	Lgnu/trove/map/TDoubleShortMap;
    //   11: aload_1
    //   12: invokeinterface 115 2 0
    //   17: aload_2
    //   18: monitorexit
    //   19: areturn
    //   20: astore_3
    //   21: aload_2
    //   22: monitorexit
    //   23: aload_3
    //   24: athrow
    // Line number table:
    //   Java source line #130	-> byte code offset #0
    // Local variable table:
    //   start	length	slot	name	signature
    //   0	25	0	this	TSynchronizedDoubleShortMap
    //   0	25	1	array	short[]
    //   5	17	2	Ljava/lang/Object;	Object
    //   20	4	3	localObject1	Object
    // Exception table:
    //   from	to	target	type
    //   7	19	20	finally
    //   20	23	20	finally
  }
  
  public TDoubleShortIterator iterator()
  {
    return this.m.iterator();
  }
  
  public double getNoEntryKey()
  {
    return this.m.getNoEntryKey();
  }
  
  public short getNoEntryValue()
  {
    return this.m.getNoEntryValue();
  }
  
  /* Error */
  public short putIfAbsent(double key, short value)
  {
    // Byte code:
    //   0: aload_0
    //   1: getfield 37	gnu/trove/impl/sync/TSynchronizedDoubleShortMap:mutex	Ljava/lang/Object;
    //   4: dup
    //   5: astore 4
    //   7: monitorenter
    //   8: aload_0
    //   9: getfield 35	gnu/trove/impl/sync/TSynchronizedDoubleShortMap:m	Lgnu/trove/map/TDoubleShortMap;
    //   12: dload_1
    //   13: iload_3
    //   14: invokeinterface 131 4 0
    //   19: aload 4
    //   21: monitorexit
    //   22: ireturn
    //   23: astore 5
    //   25: aload 4
    //   27: monitorexit
    //   28: aload 5
    //   30: athrow
    // Line number table:
    //   Java source line #142	-> byte code offset #0
    // Local variable table:
    //   start	length	slot	name	signature
    //   0	31	0	this	TSynchronizedDoubleShortMap
    //   0	31	1	key	double
    //   0	31	3	value	short
    //   5	21	4	Ljava/lang/Object;	Object
    //   23	6	5	localObject1	Object
    // Exception table:
    //   from	to	target	type
    //   8	22	23	finally
    //   23	28	23	finally
  }
  
  /* Error */
  public boolean forEachKey(gnu.trove.procedure.TDoubleProcedure procedure)
  {
    // Byte code:
    //   0: aload_0
    //   1: getfield 37	gnu/trove/impl/sync/TSynchronizedDoubleShortMap:mutex	Ljava/lang/Object;
    //   4: dup
    //   5: astore_2
    //   6: monitorenter
    //   7: aload_0
    //   8: getfield 35	gnu/trove/impl/sync/TSynchronizedDoubleShortMap:m	Lgnu/trove/map/TDoubleShortMap;
    //   11: aload_1
    //   12: invokeinterface 135 2 0
    //   17: aload_2
    //   18: monitorexit
    //   19: ireturn
    //   20: astore_3
    //   21: aload_2
    //   22: monitorexit
    //   23: aload_3
    //   24: athrow
    // Line number table:
    //   Java source line #145	-> byte code offset #0
    // Local variable table:
    //   start	length	slot	name	signature
    //   0	25	0	this	TSynchronizedDoubleShortMap
    //   0	25	1	procedure	gnu.trove.procedure.TDoubleProcedure
    //   5	17	2	Ljava/lang/Object;	Object
    //   20	4	3	localObject1	Object
    // Exception table:
    //   from	to	target	type
    //   7	19	20	finally
    //   20	23	20	finally
  }
  
  /* Error */
  public boolean forEachValue(gnu.trove.procedure.TShortProcedure procedure)
  {
    // Byte code:
    //   0: aload_0
    //   1: getfield 37	gnu/trove/impl/sync/TSynchronizedDoubleShortMap:mutex	Ljava/lang/Object;
    //   4: dup
    //   5: astore_2
    //   6: monitorenter
    //   7: aload_0
    //   8: getfield 35	gnu/trove/impl/sync/TSynchronizedDoubleShortMap:m	Lgnu/trove/map/TDoubleShortMap;
    //   11: aload_1
    //   12: invokeinterface 141 2 0
    //   17: aload_2
    //   18: monitorexit
    //   19: ireturn
    //   20: astore_3
    //   21: aload_2
    //   22: monitorexit
    //   23: aload_3
    //   24: athrow
    // Line number table:
    //   Java source line #148	-> byte code offset #0
    // Local variable table:
    //   start	length	slot	name	signature
    //   0	25	0	this	TSynchronizedDoubleShortMap
    //   0	25	1	procedure	gnu.trove.procedure.TShortProcedure
    //   5	17	2	Ljava/lang/Object;	Object
    //   20	4	3	localObject1	Object
    // Exception table:
    //   from	to	target	type
    //   7	19	20	finally
    //   20	23	20	finally
  }
  
  /* Error */
  public boolean forEachEntry(gnu.trove.procedure.TDoubleShortProcedure procedure)
  {
    // Byte code:
    //   0: aload_0
    //   1: getfield 37	gnu/trove/impl/sync/TSynchronizedDoubleShortMap:mutex	Ljava/lang/Object;
    //   4: dup
    //   5: astore_2
    //   6: monitorenter
    //   7: aload_0
    //   8: getfield 35	gnu/trove/impl/sync/TSynchronizedDoubleShortMap:m	Lgnu/trove/map/TDoubleShortMap;
    //   11: aload_1
    //   12: invokeinterface 146 2 0
    //   17: aload_2
    //   18: monitorexit
    //   19: ireturn
    //   20: astore_3
    //   21: aload_2
    //   22: monitorexit
    //   23: aload_3
    //   24: athrow
    // Line number table:
    //   Java source line #151	-> byte code offset #0
    // Local variable table:
    //   start	length	slot	name	signature
    //   0	25	0	this	TSynchronizedDoubleShortMap
    //   0	25	1	procedure	gnu.trove.procedure.TDoubleShortProcedure
    //   5	17	2	Ljava/lang/Object;	Object
    //   20	4	3	localObject1	Object
    // Exception table:
    //   from	to	target	type
    //   7	19	20	finally
    //   20	23	20	finally
  }
  
  public void transformValues(TShortFunction function)
  {
    synchronized (this.mutex)
    {
      this.m.transformValues(function);
    }
  }
  
  /* Error */
  public boolean retainEntries(gnu.trove.procedure.TDoubleShortProcedure procedure)
  {
    // Byte code:
    //   0: aload_0
    //   1: getfield 37	gnu/trove/impl/sync/TSynchronizedDoubleShortMap:mutex	Ljava/lang/Object;
    //   4: dup
    //   5: astore_2
    //   6: monitorenter
    //   7: aload_0
    //   8: getfield 35	gnu/trove/impl/sync/TSynchronizedDoubleShortMap:m	Lgnu/trove/map/TDoubleShortMap;
    //   11: aload_1
    //   12: invokeinterface 156 2 0
    //   17: aload_2
    //   18: monitorexit
    //   19: ireturn
    //   20: astore_3
    //   21: aload_2
    //   22: monitorexit
    //   23: aload_3
    //   24: athrow
    // Line number table:
    //   Java source line #157	-> byte code offset #0
    // Local variable table:
    //   start	length	slot	name	signature
    //   0	25	0	this	TSynchronizedDoubleShortMap
    //   0	25	1	procedure	gnu.trove.procedure.TDoubleShortProcedure
    //   5	17	2	Ljava/lang/Object;	Object
    //   20	4	3	localObject1	Object
    // Exception table:
    //   from	to	target	type
    //   7	19	20	finally
    //   20	23	20	finally
  }
  
  /* Error */
  public boolean increment(double key)
  {
    // Byte code:
    //   0: aload_0
    //   1: getfield 37	gnu/trove/impl/sync/TSynchronizedDoubleShortMap:mutex	Ljava/lang/Object;
    //   4: dup
    //   5: astore_3
    //   6: monitorenter
    //   7: aload_0
    //   8: getfield 35	gnu/trove/impl/sync/TSynchronizedDoubleShortMap:m	Lgnu/trove/map/TDoubleShortMap;
    //   11: dload_1
    //   12: invokeinterface 159 3 0
    //   17: aload_3
    //   18: monitorexit
    //   19: ireturn
    //   20: astore 4
    //   22: aload_3
    //   23: monitorexit
    //   24: aload 4
    //   26: athrow
    // Line number table:
    //   Java source line #160	-> byte code offset #0
    // Local variable table:
    //   start	length	slot	name	signature
    //   0	27	0	this	TSynchronizedDoubleShortMap
    //   0	27	1	key	double
    //   5	18	3	Ljava/lang/Object;	Object
    //   20	5	4	localObject1	Object
    // Exception table:
    //   from	to	target	type
    //   7	19	20	finally
    //   20	24	20	finally
  }
  
  /* Error */
  public boolean adjustValue(double key, short amount)
  {
    // Byte code:
    //   0: aload_0
    //   1: getfield 37	gnu/trove/impl/sync/TSynchronizedDoubleShortMap:mutex	Ljava/lang/Object;
    //   4: dup
    //   5: astore 4
    //   7: monitorenter
    //   8: aload_0
    //   9: getfield 35	gnu/trove/impl/sync/TSynchronizedDoubleShortMap:m	Lgnu/trove/map/TDoubleShortMap;
    //   12: dload_1
    //   13: iload_3
    //   14: invokeinterface 163 4 0
    //   19: aload 4
    //   21: monitorexit
    //   22: ireturn
    //   23: astore 5
    //   25: aload 4
    //   27: monitorexit
    //   28: aload 5
    //   30: athrow
    // Line number table:
    //   Java source line #163	-> byte code offset #0
    // Local variable table:
    //   start	length	slot	name	signature
    //   0	31	0	this	TSynchronizedDoubleShortMap
    //   0	31	1	key	double
    //   0	31	3	amount	short
    //   5	21	4	Ljava/lang/Object;	Object
    //   23	6	5	localObject1	Object
    // Exception table:
    //   from	to	target	type
    //   8	22	23	finally
    //   23	28	23	finally
  }
  
  /* Error */
  public short adjustOrPutValue(double key, short adjust_amount, short put_amount)
  {
    // Byte code:
    //   0: aload_0
    //   1: getfield 37	gnu/trove/impl/sync/TSynchronizedDoubleShortMap:mutex	Ljava/lang/Object;
    //   4: dup
    //   5: astore 5
    //   7: monitorenter
    //   8: aload_0
    //   9: getfield 35	gnu/trove/impl/sync/TSynchronizedDoubleShortMap:m	Lgnu/trove/map/TDoubleShortMap;
    //   12: dload_1
    //   13: iload_3
    //   14: iload 4
    //   16: invokeinterface 168 5 0
    //   21: aload 5
    //   23: monitorexit
    //   24: ireturn
    //   25: astore 6
    //   27: aload 5
    //   29: monitorexit
    //   30: aload 6
    //   32: athrow
    // Line number table:
    //   Java source line #166	-> byte code offset #0
    // Local variable table:
    //   start	length	slot	name	signature
    //   0	33	0	this	TSynchronizedDoubleShortMap
    //   0	33	1	key	double
    //   0	33	3	adjust_amount	short
    //   0	33	4	put_amount	short
    //   5	23	5	Ljava/lang/Object;	Object
    //   25	6	6	localObject1	Object
    // Exception table:
    //   from	to	target	type
    //   8	24	25	finally
    //   25	30	25	finally
  }
  
  /* Error */
  public boolean equals(Object o)
  {
    // Byte code:
    //   0: aload_0
    //   1: getfield 37	gnu/trove/impl/sync/TSynchronizedDoubleShortMap:mutex	Ljava/lang/Object;
    //   4: dup
    //   5: astore_2
    //   6: monitorenter
    //   7: aload_0
    //   8: getfield 35	gnu/trove/impl/sync/TSynchronizedDoubleShortMap:m	Lgnu/trove/map/TDoubleShortMap;
    //   11: aload_1
    //   12: invokevirtual 174	java/lang/Object:equals	(Ljava/lang/Object;)Z
    //   15: aload_2
    //   16: monitorexit
    //   17: ireturn
    //   18: astore_3
    //   19: aload_2
    //   20: monitorexit
    //   21: aload_3
    //   22: athrow
    // Line number table:
    //   Java source line #170	-> byte code offset #0
    // Local variable table:
    //   start	length	slot	name	signature
    //   0	23	0	this	TSynchronizedDoubleShortMap
    //   0	23	1	o	Object
    //   5	15	2	Ljava/lang/Object;	Object
    //   18	4	3	localObject1	Object
    // Exception table:
    //   from	to	target	type
    //   7	17	18	finally
    //   18	21	18	finally
  }
  
  /* Error */
  public int hashCode()
  {
    // Byte code:
    //   0: aload_0
    //   1: getfield 37	gnu/trove/impl/sync/TSynchronizedDoubleShortMap:mutex	Ljava/lang/Object;
    //   4: dup
    //   5: astore_1
    //   6: monitorenter
    //   7: aload_0
    //   8: getfield 35	gnu/trove/impl/sync/TSynchronizedDoubleShortMap:m	Lgnu/trove/map/TDoubleShortMap;
    //   11: invokevirtual 178	java/lang/Object:hashCode	()I
    //   14: aload_1
    //   15: monitorexit
    //   16: ireturn
    //   17: astore_2
    //   18: aload_1
    //   19: monitorexit
    //   20: aload_2
    //   21: athrow
    // Line number table:
    //   Java source line #173	-> byte code offset #0
    // Local variable table:
    //   start	length	slot	name	signature
    //   0	22	0	this	TSynchronizedDoubleShortMap
    //   5	14	1	Ljava/lang/Object;	Object
    //   17	4	2	localObject1	Object
    // Exception table:
    //   from	to	target	type
    //   7	16	17	finally
    //   17	20	17	finally
  }
  
  /* Error */
  public String toString()
  {
    // Byte code:
    //   0: aload_0
    //   1: getfield 37	gnu/trove/impl/sync/TSynchronizedDoubleShortMap:mutex	Ljava/lang/Object;
    //   4: dup
    //   5: astore_1
    //   6: monitorenter
    //   7: aload_0
    //   8: getfield 35	gnu/trove/impl/sync/TSynchronizedDoubleShortMap:m	Lgnu/trove/map/TDoubleShortMap;
    //   11: invokevirtual 182	java/lang/Object:toString	()Ljava/lang/String;
    //   14: aload_1
    //   15: monitorexit
    //   16: areturn
    //   17: astore_2
    //   18: aload_1
    //   19: monitorexit
    //   20: aload_2
    //   21: athrow
    // Line number table:
    //   Java source line #176	-> byte code offset #0
    // Local variable table:
    //   start	length	slot	name	signature
    //   0	22	0	this	TSynchronizedDoubleShortMap
    //   5	14	1	Ljava/lang/Object;	Object
    //   17	4	2	localObject1	Object
    // Exception table:
    //   from	to	target	type
    //   7	16	17	finally
    //   17	20	17	finally
  }
  
  private void writeObject(ObjectOutputStream s)
    throws IOException
  {
    synchronized (this.mutex)
    {
      s.defaultWriteObject();
    }
  }
}
